README.md
setup.cfg
setup.py
myapiframework/__init__.py
myapiframework/backends.py
myapiframework/exceptions.py
myapiframework/fields.py
myapiframework/myapiframework.py
myapiframework/parser.py
myapiframework/request.py
myapiframework/response.py
myapiframework.egg-info/PKG-INFO
myapiframework.egg-info/SOURCES.txt
myapiframework.egg-info/dependency_links.txt
myapiframework.egg-info/requires.txt
myapiframework.egg-info/top_level.txt