Metadata-Version: 2.1
Name: myapiframework
Version: 1.0
Summary: eazy python framework
Home-page: https://github.com/Barashov/Myapi
Author: Barashov
Author-email: barashovmisha@gmail.com
